paddy/Default_Numerics.py
paddy/Paddy_Parameter.py
paddy/Paddy_Runner.py
paddy/__init__.py
paddy/exceptions.py
paddy/utils.py
paddy/writer.py
paddy/tests/__init__.py
paddy/tests/paddy_test.py
paddy-0.2.3.dist-info/LICENSE
paddy-0.2.3.dist-info/METADATA
paddy-0.2.3.dist-info/WHEEL
paddy-0.2.3.dist-info/top_level.txt
paddy-0.2.3.dist-info/RECORD
