Metadata-Version: 2.1
Name: paddy
Version: 0.2.3
Summary: Optimize hyperparameters using the Paddy field algorithm
Home-page: http://github.com/chopralab/paddy
Author: Armen Beck
Author-email: armengbeck@gmail.com
Keywords: paddyfield optimization hyperparameter model selection
Classifier: Development Status :: 4 - Beta
Classifier: Environment :: Console
Classifier: Intended Audience :: Developers
Classifier: Intended Audience :: Science/Research
Classifier: License :: OSI Approved :: BSD License
Classifier: Operating System :: MacOS :: MacOS X
Classifier: Operating System :: Microsoft :: Windows
Classifier: Operating System :: Unix
Classifier: Programming Language :: Python :: 2.7
Classifier: Programming Language :: Python :: 3.6
Classifier: Programming Language :: Python :: 3.7
Classifier: Programming Language :: Python :: 3.9
Classifier: Programming Language :: Python :: 3.10
Classifier: Topic :: Scientific/Engineering
Classifier: Topic :: Software Development
License-File: LICENSE
Requires-Dist: scipy
Requires-Dist: future
Requires-Dist: numpy
Requires-Dist: matplotlib
